dockmaster/__init__.py
dockmaster/__main__.py
dockmaster/cli.py
dockmaster/cli_utils.py
dockmaster/constants.py
dockmaster/interactive.py
dockmaster/interactive_utils.py
dockmaster/time_utils.py
dockmaster/utils.py
dockmaster/commands/__init__.py
dockmaster/commands/schedule.py
dockmaster/formatters/status.py
dockmaster/managers/__init__.py
dockmaster/managers/base_manager.py
dockmaster/managers/config_manager.py
dockmaster/managers/container_manager.py
dockmaster/managers/image_manager.py
dockmaster/managers/project_manager.py
dockmaster/managers/scheduler_daemon.py
dockmaster-0.2.1.dist-info/METADATA
dockmaster-0.2.1.dist-info/WHEEL
dockmaster-0.2.1.dist-info/entry_points.txt
dockmaster-0.2.1.dist-info/top_level.txt
dockmaster-0.2.1.dist-info/RECORD
