Metadata-Version: 2.2
Name: dockmaster
Version: 0.2.1
Summary: Docker项目和容器管理工具
Home-page: https://github.com/queekye/dockmaster
Author: Kang Chen
Author-email: chenkangcs@foxmail.com
Project-URL: Bug Tracker, https://github.com/queekye/dockmaster/issues
Project-URL: Documentation, https://github.com/queekye/dockmaster/wiki
Project-URL: Source Code, https://github.com/queekye/dockmaster
Keywords: docker,container,management,devops,automation
Classifier: Development Status :: 3 - Alpha
Classifier: Intended Audience :: Developers
Classifier: Intended Audience :: System Administrators
Classifier: Intended Audience :: Information Technology
Classifier: Topic :: Software Development :: Build Tools
Classifier: Topic :: System :: Systems Administration
Classifier: Topic :: Utilities
Classifier: License :: OSI Approved :: MIT License
Classifier: Programming Language :: Python :: 3
Classifier: Programming Language :: Python :: 3.8
Classifier: Programming Language :: Python :: 3.9
Classifier: Programming Language :: Python :: 3.10
Classifier: Programming Language :: Python :: 3.11
Classifier: Operating System :: OS Independent
Requires-Python: >=3.8
Requires-Dist: docker>=7.0.0
Requires-Dist: typer[all]>=0.9.0
Requires-Dist: colorlog>=6.7.0
Requires-Dist: pyyaml>=6.0
Requires-Dist: rich>=13.4.2
Requires-Dist: python-dotenv>=1.0.0
Requires-Dist: questionary>=2.0.0
Requires-Dist: click>=8.0.0
Requires-Dist: shellingham>=1.5.0
Requires-Dist: croniter>=2.0.0
Requires-Dist: schedule
Requires-Dist: loguru>=0.7.0
Dynamic: author
Dynamic: author-email
Dynamic: classifier
Dynamic: description
Dynamic: description-content-type
Dynamic: home-page
Dynamic: keywords
Dynamic: project-url
Dynamic: requires-dist
Dynamic: requires-python
Dynamic: summary
